README.md
setup.py
newitem_video/Videos.py
newitem_video/__init__.py
newitem_video/database.py
newitem_video.egg-info/PKG-INFO
newitem_video.egg-info/SOURCES.txt
newitem_video.egg-info/dependency_links.txt
newitem_video.egg-info/requires.txt
newitem_video.egg-info/top_level.txt