Metadata-Version: 1.0
Name: newitem-video
Version: 0.0.1
Summary: newitem-db-video
Home-page: UNKNOWN
Author: UNKNOWN
Author-email: originman@bluehack.net
License: UNKNOWN
Keywords: Newitem,newitem-db-video
Platform: UNKNOWN
